.coveragerc
.gitignore
.travis.yml
MANIFEST.in
README.rst
requirements.txt
runtests.py
setup.py
facebookpagewriter/__init__.py
facebookpagewriter/models.py
facebookpagewriter/urls.py
facebookpagewriter/utils.py
facebookpagewriter/views.py
facebookpagewriter.egg-info/PKG-INFO
facebookpagewriter.egg-info/SOURCES.txt
facebookpagewriter.egg-info/dependency_links.txt
facebookpagewriter.egg-info/requires.txt
facebookpagewriter.egg-info/top_level.txt
facebookpagewriter/tests/__init__.py
facebookpagewriter/tests/tests.py