Metadata-Version: 1.1
Name: facebookpagewriter
Version: 0.10
Summary: Automate Facebook page posting
Home-page: http://github.com/codesyntax/facebookpagewriter
Author: Aitzol Naberan
Author-email: anaberan@codesyntax.com
License: UNKNOWN
Platform: UNKNOWN
Classifier: Development Status :: 5 - Production/Stable
Classifier: Environment :: Web Environment
Classifier: Framework :: Django
Classifier: Intended Audience :: Developers
Classifier: License :: OSI Approved :: BSD License
Classifier: Operating System :: OS Independent
Classifier: Programming Language :: Python
Classifier: Programming Language :: Python :: 2.7
Classifier: Programming Language :: Python :: 3.7
Classifier: Topic :: Software Development :: Libraries :: Python Modules
Classifier: Topic :: Utilities
